{
  "trial_id": 311,
  "trial_name": "trial_311_transformer",
  "model": "transformer",
  "best_epoch": 82,
  "elapsed_sec": 280.1906042098999,
  "direct_mae": 0.00215769256465137,
  "direct_rmse": 0.0028498992323875427,
  "direct_r2": 0.9999915454327493,
  "direct_valid_ratio": 1.0,
  "direct_residual_mean": 0.002642494859173894,
  "direct_residual_median": 0.0019844770431518555,
  "direct_residual_p90": 0.005879124999046327,
  "plus_newton_mae": 2.3433619539545264e-08,
  "plus_newton_rmse": 2.991573082070916e-08,
  "plus_newton_r2": 0.9999999999999991,
  "plus_newton_valid_ratio": 1.0,
  "plus_newton_residual_mean": 3.1235431735820173e-14,
  "plus_newton_residual_median": 1.1102230246251565e-16,
  "plus_newton_residual_p90": 3.863576125695545e-14,
  "plus_newton_newton_iter_mean": 2.0194,
  "plus_newton_newton_iter_median": 2.0,
  "plus_newton_newton_iter_p90": 2.0,
  "plus_newton_converged_ratio": 1.0,
  "hp_use_log_ab": false,
  "hp_optimizer": "adamw",
  "hp_criterion": "mse",
  "hp_dropout": 0.0,
  "hp_lr": 0.0005,
  "hp_weight_decay": 1e-05,
  "hp_hidden_dims": "[256, 256, 128]",
  "hp_hidden_size": 128,
  "hp_num_layers": 1,
  "hp_head_hidden": 128,
  "hp_head_layers": 2,
  "hp_d_model": 32,
  "hp_nhead": 4,
  "hp_ff_dim": 128,
  "hp_use_cls_token": false
}{
  "trial_id": 311,
  "trial_name": "trial_311_transformer",
  "model": "transformer",
  "best_epoch": 82,
  "elapsed_sec": 280.1906042098999,
  "direct_mae": 0.00215769256465137,
  "direct_rmse": 0.0028498992323875427,
  "direct_r2": 0.9999915454327493,
  "direct_valid_ratio": 1.0,
  "direct_residual_mean": 0.002642494859173894,
  "direct_residual_median": 0.0019844770431518555,
  "direct_residual_p90": 0.005879124999046327,
  "plus_newton_mae": 2.3433619539545264e-08,
  "plus_newton_rmse": 2.991573082070916e-08,
  "plus_newton_r2": 0.9999999999999991,
  "plus_newton_valid_ratio": 1.0,
  "plus_newton_residual_mean": 3.1235431735820173e-14,
  "plus_newton_residual_median": 1.1102230246251565e-16,
  "plus_newton_residual_p90": 3.863576125695545e-14,
  "plus_newton_newton_iter_mean": 2.0194,
  "plus_newton_newton_iter_median": 2.0,
  "plus_newton_newton_iter_p90": 2.0,
  "plus_newton_converged_ratio": 1.0,
  "hp_use_log_ab": false,
  "hp_optimizer": "adamw",
  "hp_criterion": "mse",
  "hp_dropout": 0.0,
  "hp_lr": 0.0005,
  "hp_weight_decay": 1e-05,
  "hp_hidden_dims": "[256, 256, 128]",
  "hp_hidden_size": 128,
  "hp_num_layers": 1,
  "hp_head_hidden": 128,
  "hp_head_layers": 2,
  "hp_d_model": 32,
  "hp_nhead": 4,
  "hp_ff_dim": 128,
  "hp_use_cls_token": false
}