{
  "trial_id": 25,
  "trial_name": "trial_025_lstm",
  "model": "lstm",
  "best_epoch": 71,
  "elapsed_sec": 264.8366606235504,
  "direct_mae": 0.34028711915016174,
  "direct_rmse": 0.41685667634010315,
  "direct_r2": 0.8191136121749878,
  "direct_valid_ratio": 1.0,
  "direct_residual_mean": 0.38301795721054077,
  "direct_residual_median": 0.3595048189163208,
  "direct_residual_p90": 0.7231392562389375,
  "plus_newton_mae": 2.3433619773585967e-08,
  "plus_newton_rmse": 2.991573148485031e-08,
  "plus_newton_r2": 0.9999999999999991,
  "plus_newton_valid_ratio": 1.0,
  "plus_newton_residual_mean": 4.433571296744683e-14,
  "plus_newton_residual_median": 1.6653345369377348e-16,
  "plus_newton_residual_p90": 1.0397377403492685e-13,
  "plus_newton_newton_iter_mean": 2.7536,
  "plus_newton_newton_iter_median": 3.0,
  "plus_newton_newton_iter_p90": 3.0,
  "plus_newton_converged_ratio": 1.0,
  "hp_use_log_ab": false,
  "hp_optimizer": "adamw",
  "hp_criterion": "mse",
  "hp_dropout": 0.0,
  "hp_lr": 0.001,
  "hp_weight_decay": 0.0001,
  "hp_hidden_dims": "[256, 256, 128]",
  "hp_hidden_size": 128,
  "hp_num_layers": 1,
  "hp_head_hidden": 64,
  "hp_head_layers": 1,
  "hp_d_model": 64,
  "hp_nhead": 4,
  "hp_ff_dim": 128,
  "hp_use_cls_token": false
}{
  "trial_id": 25,
  "trial_name": "trial_025_lstm",
  "model": "lstm",
  "best_epoch": 71,
  "elapsed_sec": 264.8366606235504,
  "direct_mae": 0.34028711915016174,
  "direct_rmse": 0.41685667634010315,
  "direct_r2": 0.8191136121749878,
  "direct_valid_ratio": 1.0,
  "direct_residual_mean": 0.38301795721054077,
  "direct_residual_median": 0.3595048189163208,
  "direct_residual_p90": 0.7231392562389375,
  "plus_newton_mae": 2.3433619773585967e-08,
  "plus_newton_rmse": 2.991573148485031e-08,
  "plus_newton_r2": 0.9999999999999991,
  "plus_newton_valid_ratio": 1.0,
  "plus_newton_residual_mean": 4.433571296744683e-14,
  "plus_newton_residual_median": 1.6653345369377348e-16,
  "plus_newton_residual_p90": 1.0397377403492685e-13,
  "plus_newton_newton_iter_mean": 2.7536,
  "plus_newton_newton_iter_median": 3.0,
  "plus_newton_newton_iter_p90": 3.0,
  "plus_newton_converged_ratio": 1.0,
  "hp_use_log_ab": false,
  "hp_optimizer": "adamw",
  "hp_criterion": "mse",
  "hp_dropout": 0.0,
  "hp_lr": 0.001,
  "hp_weight_decay": 0.0001,
  "hp_hidden_dims": "[256, 256, 128]",
  "hp_hidden_size": 128,
  "hp_num_layers": 1,
  "hp_head_hidden": 64,
  "hp_head_layers": 1,
  "hp_d_model": 64,
  "hp_nhead": 4,
  "hp_ff_dim": 128,
  "hp_use_cls_token": false
}