{
  "trial_id": 958,
  "trial_name": "trial_958_transformer",
  "model": "transformer",
  "best_epoch": 87,
  "elapsed_sec": 156.61855101585388,
  "direct_mae": 0.007499287370592356,
  "direct_rmse": 0.011597099713981152,
  "direct_r2": 0.9998599989776267,
  "direct_valid_ratio": 1.0,
  "direct_residual_mean": 0.008771052584052086,
  "direct_residual_median": 0.005882032215595245,
  "direct_residual_p90": 0.021282994747161867,
  "plus_newton_mae": 2.3433618126036793e-08,
  "plus_newton_rmse": 2.991573015818718e-08,
  "plus_newton_r2": 0.9999999999999991,
  "plus_newton_valid_ratio": 1.0,
  "plus_newton_residual_mean": 2.597716075128815e-14,
  "plus_newton_residual_median": 1.1102230246251565e-16,
  "plus_newton_residual_p90": 2.6884050541298226e-14,
  "plus_newton_newton_iter_mean": 2.1186,
  "plus_newton_newton_iter_median": 2.0,
  "plus_newton_newton_iter_p90": 3.0,
  "plus_newton_converged_ratio": 1.0,
  "hp_use_log_ab": false,
  "hp_optimizer": "adamw",
  "hp_criterion": "mse",
  "hp_dropout": 0.1,
  "hp_lr": 0.0005,
  "hp_weight_decay": 0.0001,
  "hp_hidden_dims": "[256, 256, 128]",
  "hp_hidden_size": 128,
  "hp_num_layers": 1,
  "hp_head_hidden": 128,
  "hp_head_layers": 2,
  "hp_d_model": 64,
  "hp_nhead": 4,
  "hp_ff_dim": 64,
  "hp_use_cls_token": true
}{
  "trial_id": 958,
  "trial_name": "trial_958_transformer",
  "model": "transformer",
  "best_epoch": 87,
  "elapsed_sec": 156.61855101585388,
  "direct_mae": 0.007499287370592356,
  "direct_rmse": 0.011597099713981152,
  "direct_r2": 0.9998599989776267,
  "direct_valid_ratio": 1.0,
  "direct_residual_mean": 0.008771052584052086,
  "direct_residual_median": 0.005882032215595245,
  "direct_residual_p90": 0.021282994747161867,
  "plus_newton_mae": 2.3433618126036793e-08,
  "plus_newton_rmse": 2.991573015818718e-08,
  "plus_newton_r2": 0.9999999999999991,
  "plus_newton_valid_ratio": 1.0,
  "plus_newton_residual_mean": 2.597716075128815e-14,
  "plus_newton_residual_median": 1.1102230246251565e-16,
  "plus_newton_residual_p90": 2.6884050541298226e-14,
  "plus_newton_newton_iter_mean": 2.1186,
  "plus_newton_newton_iter_median": 2.0,
  "plus_newton_newton_iter_p90": 3.0,
  "plus_newton_converged_ratio": 1.0,
  "hp_use_log_ab": false,
  "hp_optimizer": "adamw",
  "hp_criterion": "mse",
  "hp_dropout": 0.1,
  "hp_lr": 0.0005,
  "hp_weight_decay": 0.0001,
  "hp_hidden_dims": "[256, 256, 128]",
  "hp_hidden_size": 128,
  "hp_num_layers": 1,
  "hp_head_hidden": 128,
  "hp_head_layers": 2,
  "hp_d_model": 64,
  "hp_nhead": 4,
  "hp_ff_dim": 64,
  "hp_use_cls_token": true
}