{
  "trial_id": 1192,
  "trial_name": "trial_1192_transformer",
  "model": "transformer",
  "best_epoch": 16,
  "elapsed_sec": 50.3454966545105,
  "direct_mae": 0.3386768102645874,
  "direct_rmse": 0.4187954366207123,
  "direct_r2": 0.8174271136522293,
  "direct_valid_ratio": 1.0,
  "direct_residual_mean": 0.3832768201828003,
  "direct_residual_median": 0.3503578007221222,
  "direct_residual_p90": 0.7686617016792299,
  "plus_newton_mae": 2.3433618995330053e-08,
  "plus_newton_rmse": 2.9915731188074936e-08,
  "plus_newton_r2": 0.9999999999999991,
  "plus_newton_valid_ratio": 1.0,
  "plus_newton_residual_mean": 4.4742734564896416e-14,
  "plus_newton_residual_median": 1.6653345369377348e-16,
  "plus_newton_residual_p90": 1.0792478022381151e-13,
  "plus_newton_newton_iter_mean": 2.7618,
  "plus_newton_newton_iter_median": 3.0,
  "plus_newton_newton_iter_p90": 3.0,
  "plus_newton_converged_ratio": 1.0,
  "hp_use_log_ab": false,
  "hp_optimizer": "adamw",
  "hp_criterion": "smoothl1",
  "hp_dropout": 0.0,
  "hp_lr": 0.001,
  "hp_weight_decay": 0.0001,
  "hp_hidden_dims": "[256, 256, 128]",
  "hp_hidden_size": 128,
  "hp_num_layers": 1,
  "hp_head_hidden": 128,
  "hp_head_layers": 1,
  "hp_d_model": 32,
  "hp_nhead": 4,
  "hp_ff_dim": 128,
  "hp_use_cls_token": true
}{
  "trial_id": 1192,
  "trial_name": "trial_1192_transformer",
  "model": "transformer",
  "best_epoch": 16,
  "elapsed_sec": 50.3454966545105,
  "direct_mae": 0.3386768102645874,
  "direct_rmse": 0.4187954366207123,
  "direct_r2": 0.8174271136522293,
  "direct_valid_ratio": 1.0,
  "direct_residual_mean": 0.3832768201828003,
  "direct_residual_median": 0.3503578007221222,
  "direct_residual_p90": 0.7686617016792299,
  "plus_newton_mae": 2.3433618995330053e-08,
  "plus_newton_rmse": 2.9915731188074936e-08,
  "plus_newton_r2": 0.9999999999999991,
  "plus_newton_valid_ratio": 1.0,
  "plus_newton_residual_mean": 4.4742734564896416e-14,
  "plus_newton_residual_median": 1.6653345369377348e-16,
  "plus_newton_residual_p90": 1.0792478022381151e-13,
  "plus_newton_newton_iter_mean": 2.7618,
  "plus_newton_newton_iter_median": 3.0,
  "plus_newton_newton_iter_p90": 3.0,
  "plus_newton_converged_ratio": 1.0,
  "hp_use_log_ab": false,
  "hp_optimizer": "adamw",
  "hp_criterion": "smoothl1",
  "hp_dropout": 0.0,
  "hp_lr": 0.001,
  "hp_weight_decay": 0.0001,
  "hp_hidden_dims": "[256, 256, 128]",
  "hp_hidden_size": 128,
  "hp_num_layers": 1,
  "hp_head_hidden": 128,
  "hp_head_layers": 1,
  "hp_d_model": 32,
  "hp_nhead": 4,
  "hp_ff_dim": 128,
  "hp_use_cls_token": true
}