{
  "trial_id": 201,
  "trial_name": "trial_201_lstm",
  "model": "lstm",
  "best_epoch": 24,
  "elapsed_sec": 109.75079345703125,
  "direct_mae": 0.3383048474788666,
  "direct_rmse": 0.41953954100608826,
  "direct_r2": 0.816777765750885,
  "direct_valid_ratio": 1.0,
  "direct_residual_mean": 0.3816585838794708,
  "direct_residual_median": 0.3490046560764313,
  "direct_residual_p90": 0.7668977856636053,
  "plus_newton_mae": 2.3433617976744565e-08,
  "plus_newton_rmse": 2.991573031742901e-08,
  "plus_newton_r2": 0.9999999999999991,
  "plus_newton_valid_ratio": 1.0,
  "plus_newton_residual_mean": 4.481476623605831e-14,
  "plus_newton_residual_median": 1.3097162243624894e-16,
  "plus_newton_residual_p90": 1.085145862056437e-13,
  "plus_newton_newton_iter_mean": 2.7561,
  "plus_newton_newton_iter_median": 3.0,
  "plus_newton_newton_iter_p90": 3.0,
  "plus_newton_converged_ratio": 1.0,
  "hp_use_log_ab": false,
  "hp_optimizer": "adamw",
  "hp_criterion": "smoothl1",
  "hp_dropout": 0.1,
  "hp_lr": 0.001,
  "hp_weight_decay": 1e-05,
  "hp_hidden_dims": "[256, 256, 128]",
  "hp_hidden_size": 128,
  "hp_num_layers": 1,
  "hp_head_hidden": 64,
  "hp_head_layers": 1,
  "hp_d_model": 64,
  "hp_nhead": 4,
  "hp_ff_dim": 128,
  "hp_use_cls_token": false
}{
  "trial_id": 201,
  "trial_name": "trial_201_lstm",
  "model": "lstm",
  "best_epoch": 24,
  "elapsed_sec": 109.75079345703125,
  "direct_mae": 0.3383048474788666,
  "direct_rmse": 0.41953954100608826,
  "direct_r2": 0.816777765750885,
  "direct_valid_ratio": 1.0,
  "direct_residual_mean": 0.3816585838794708,
  "direct_residual_median": 0.3490046560764313,
  "direct_residual_p90": 0.7668977856636053,
  "plus_newton_mae": 2.3433617976744565e-08,
  "plus_newton_rmse": 2.991573031742901e-08,
  "plus_newton_r2": 0.9999999999999991,
  "plus_newton_valid_ratio": 1.0,
  "plus_newton_residual_mean": 4.481476623605831e-14,
  "plus_newton_residual_median": 1.3097162243624894e-16,
  "plus_newton_residual_p90": 1.085145862056437e-13,
  "plus_newton_newton_iter_mean": 2.7561,
  "plus_newton_newton_iter_median": 3.0,
  "plus_newton_newton_iter_p90": 3.0,
  "plus_newton_converged_ratio": 1.0,
  "hp_use_log_ab": false,
  "hp_optimizer": "adamw",
  "hp_criterion": "smoothl1",
  "hp_dropout": 0.1,
  "hp_lr": 0.001,
  "hp_weight_decay": 1e-05,
  "hp_hidden_dims": "[256, 256, 128]",
  "hp_hidden_size": 128,
  "hp_num_layers": 1,
  "hp_head_hidden": 64,
  "hp_head_layers": 1,
  "hp_d_model": 64,
  "hp_nhead": 4,
  "hp_ff_dim": 128,
  "hp_use_cls_token": false
}