{
  "trial_id": 122,
  "trial_name": "trial_122_lstm",
  "model": "lstm",
  "best_epoch": 96,
  "elapsed_sec": 127.17916178703308,
  "direct_mae": 0.001970935147255659,
  "direct_rmse": 0.0027076746337115765,
  "direct_r2": 0.9999923682280496,
  "direct_valid_ratio": 1.0,
  "direct_residual_mean": 0.0023371942806988955,
  "direct_residual_median": 0.0017105340957641602,
  "direct_residual_p90": 0.005276289582252504,
  "plus_newton_mae": 2.3433617685992294e-08,
  "plus_newton_rmse": 2.9915730451479746e-08,
  "plus_newton_r2": 0.9999999999999991,
  "plus_newton_valid_ratio": 1.0,
  "plus_newton_residual_mean": 2.5419312979253483e-14,
  "plus_newton_residual_median": 1.1102230246251565e-16,
  "plus_newton_residual_p90": 1.943722960362496e-14,
  "plus_newton_newton_iter_mean": 1.9999,
  "plus_newton_newton_iter_median": 2.0,
  "plus_newton_newton_iter_p90": 2.0,
  "plus_newton_converged_ratio": 1.0,
  "hp_use_log_ab": false,
  "hp_optimizer": "adamw",
  "hp_criterion": "mse",
  "hp_dropout": 0.0,
  "hp_lr": 0.001,
  "hp_weight_decay": 0.0001,
  "hp_hidden_dims": "[256, 256, 128]",
  "hp_hidden_size": 128,
  "hp_num_layers": 1,
  "hp_head_hidden": 64,
  "hp_head_layers": 2,
  "hp_d_model": 64,
  "hp_nhead": 4,
  "hp_ff_dim": 128,
  "hp_use_cls_token": false
}{
  "trial_id": 122,
  "trial_name": "trial_122_lstm",
  "model": "lstm",
  "best_epoch": 96,
  "elapsed_sec": 127.17916178703308,
  "direct_mae": 0.001970935147255659,
  "direct_rmse": 0.0027076746337115765,
  "direct_r2": 0.9999923682280496,
  "direct_valid_ratio": 1.0,
  "direct_residual_mean": 0.0023371942806988955,
  "direct_residual_median": 0.0017105340957641602,
  "direct_residual_p90": 0.005276289582252504,
  "plus_newton_mae": 2.3433617685992294e-08,
  "plus_newton_rmse": 2.9915730451479746e-08,
  "plus_newton_r2": 0.9999999999999991,
  "plus_newton_valid_ratio": 1.0,
  "plus_newton_residual_mean": 2.5419312979253483e-14,
  "plus_newton_residual_median": 1.1102230246251565e-16,
  "plus_newton_residual_p90": 1.943722960362496e-14,
  "plus_newton_newton_iter_mean": 1.9999,
  "plus_newton_newton_iter_median": 2.0,
  "plus_newton_newton_iter_p90": 2.0,
  "plus_newton_converged_ratio": 1.0,
  "hp_use_log_ab": false,
  "hp_optimizer": "adamw",
  "hp_criterion": "mse",
  "hp_dropout": 0.0,
  "hp_lr": 0.001,
  "hp_weight_decay": 0.0001,
  "hp_hidden_dims": "[256, 256, 128]",
  "hp_hidden_size": 128,
  "hp_num_layers": 1,
  "hp_head_hidden": 64,
  "hp_head_layers": 2,
  "hp_d_model": 64,
  "hp_nhead": 4,
  "hp_ff_dim": 128,
  "hp_use_cls_token": false
}