{
  "degree": 20,
  "model": "mlp",
  "trial_dir": "mlp_trial_013_mlp",
  "run_dir": "run_042",
  "seed": 42,
  "n_samples": 10000,
  "device": "cuda",
  "batch_size": 4096,
  "model_path": "/root/project/dataset/math_03_14/hybrid_params2_runs/deg20/mlp_trial_013_mlp/run_042/train/best_model.pt",
  "test_npz": "/root/project/dataset/math_03_14/multi_colebrook_data_deg20/parallel2_colebrook_deg20_test.npz",
  "best_epoch": 635,
  "best_val_rmse": 0.00043542153434827924,
  "direct_mae": 0.00020109556240018595,
  "direct_rmse": 0.00037554519231510977,
  "direct_r2": 0.9999996323899144,
  "preprocessing_ms_per_sample": 0.22579085499746726,
  "forward_gpu_ms_per_sample_mean": 0.002871810048430537,
  "forward_gpu_ms_per_sample_std": 0.0007724978164837359,
  "forward_gpu_ms_per_sample_min": 0.0004884882015176118,
  "forward_gpu_ms_per_sample_max": 0.0038047648034989835,
  "forward_with_copy_ms_per_sample_mean": 0.006362697652075438,
  "forward_with_copy_ms_per_sample_std": 0.0012298038231354797,
  "forward_with_copy_ms_per_sample_min": 0.003763719997368753,
  "forward_with_copy_ms_per_sample_max": 0.009013672603759914,
  "neural_direct_total_ms_per_sample": 0.2321535526495427,
  "heuristic_newton_ms_per_sample": 2.134173980203923,
  "neural_newton_ms_per_sample": 0.8013531439937651,
  "neural_end_to_end_ms_per_sample": 1.0335066966433077,
  "heuristic_newton_iter_mean": 5.9136,
  "neural_newton_iter_mean": 2.3235,
  "heuristic_newton_converged_ratio": 0.9999,
  "neural_newton_converged_ratio": 1.0,
  "forward_repeats": 30,
  "forward_warmup": 5,
  "newton_repeats": 1
}