{
  "heuristic_direct": {
    "mae": {
      "mean": 0.09710039504512848,
      "std": 0.0,
      "min": 0.09710039504512848,
      "max": 0.09710039504512848
    },
    "rmse": {
      "mean": 0.21025729362344586,
      "std": 0.0,
      "min": 0.21025729362344586,
      "max": 0.21025729362344586
    },
    "r2": {
      "mean": 0.8834746074576723,
      "std": 0.0,
      "min": 0.8834746074576723,
      "max": 0.8834746074576723
    },
    "valid_ratio": {
      "mean": 1.0,
      "std": 0.0,
      "min": 1.0,
      "max": 1.0
    },
    "residual_mean": {
      "mean": 103.26627398539918,
      "std": 0.0,
      "min": 103.26627398539918,
      "max": 103.26627398539918
    },
    "residual_median": {
      "mean": 0.9996288204594204,
      "std": 0.0,
      "min": 0.9996288204594204,
      "max": 0.9996288204594204
    },
    "residual_p90": {
      "mean": 126.51098781810394,
      "std": 0.0,
      "min": 126.51098781810394,
      "max": 126.51098781810394
    },
    "max_abs_error": {
      "mean": 3.5184905443307604,
      "std": 0.0,
      "min": 3.5184905443307604,
      "max": 3.5184905443307604
    },
    "newton_iter_mean": {
      "mean": NaN,
      "std": NaN,
      "min": NaN,
      "max": NaN
    },
    "newton_iter_median": {
      "mean": NaN,
      "std": NaN,
      "min": NaN,
      "max": NaN
    },
    "newton_iter_p90": {
      "mean": NaN,
      "std": NaN,
      "min": NaN,
      "max": NaN
    },
    "newton_converged_ratio": {
      "mean": NaN,
      "std": NaN,
      "min": NaN,
      "max": NaN
    }
  },
  "heuristic_plus_newton": {
    "mae": {
      "mean": 2.6035335929106006e-10,
      "std": 0.0,
      "min": 2.6035335929106006e-10,
      "max": 2.6035335929106006e-10
    },
    "rmse": {
      "mean": 3.6813604170292685e-09,
      "std": 0.0,
      "min": 3.6813604170292685e-09,
      "max": 3.6813604170292685e-09
    },
    "r2": {
      "mean": 1.0,
      "std": 0.0,
      "min": 1.0,
      "max": 1.0
    },
    "valid_ratio": {
      "mean": 1.0,
      "std": 0.0,
      "min": 1.0,
      "max": 1.0
    },
    "residual_mean": {
      "mean": 5.513936018776112e-12,
      "std": 0.0,
      "min": 5.513936018776112e-12,
      "max": 5.513936018776112e-12
    },
    "residual_median": {
      "mean": 8.881784197001252e-16,
      "std": 0.0,
      "min": 8.881784197001252e-16,
      "max": 8.881784197001252e-16
    },
    "residual_p90": {
      "mean": 1.7009171848769703e-13,
      "std": 0.0,
      "min": 1.7009171848769703e-13,
      "max": 1.7009171848769703e-13
    },
    "max_abs_error": {
      "mean": 8.615343933815467e-07,
      "std": 0.0,
      "min": 8.615343933815467e-07,
      "max": 8.615343933815467e-07
    },
    "newton_iter_mean": {
      "mean": 5.925075,
      "std": 0.0,
      "min": 5.925075,
      "max": 5.925075
    },
    "newton_iter_median": {
      "mean": 6.0,
      "std": 0.0,
      "min": 6.0,
      "max": 6.0
    },
    "newton_iter_p90": {
      "mean": 9.0,
      "std": 0.0,
      "min": 9.0,
      "max": 9.0
    },
    "newton_converged_ratio": {
      "mean": 0.9999,
      "std": 0.0,
      "min": 0.9999,
      "max": 0.9999
    }
  },
  "neural_direct": {
    "mae": {
      "mean": 0.0008886954874488736,
      "std": 0.00010524549015505508,
      "min": 0.0007389117645286316,
      "max": 0.001141542578706574
    },
    "rmse": {
      "mean": 0.0016686686119134536,
      "std": 0.00017589756085477308,
      "min": 0.0014113975242865883,
      "max": 0.0020153259755145442
    },
    "r2": {
      "mean": 0.9999925807110079,
      "std": 1.5922156199354907e-06,
      "min": 0.9999892944486304,
      "max": 0.9999947493008247
    },
    "valid_ratio": {
      "mean": 1.0,
      "std": 0.0,
      "min": 1.0,
      "max": 1.0
    },
    "residual_mean": {
      "mean": 0.01713997873315217,
      "std": 0.0044160009293140925,
      "min": 0.009505910073653107,
      "max": 0.032272403501545935
    },
    "residual_median": {
      "mean": 0.0026986095139342014,
      "std": 0.0004426578630968367,
      "min": 0.00198797367025888,
      "max": 0.0035955888906646083
    },
    "residual_p90": {
      "mean": 0.01927283926017139,
      "std": 0.005051665142956357,
      "min": 0.012075736043817637,
      "max": 0.03467256395147549
    },
    "max_abs_error": {
      "mean": 0.06283407916209222,
      "std": 0.011749084108027332,
      "min": 0.03796073232925323,
      "max": 0.08839906540592057
    },
    "newton_iter_mean": {
      "mean": NaN,
      "std": NaN,
      "min": NaN,
      "max": NaN
    },
    "newton_iter_median": {
      "mean": NaN,
      "std": NaN,
      "min": NaN,
      "max": NaN
    },
    "newton_iter_p90": {
      "mean": NaN,
      "std": NaN,
      "min": NaN,
      "max": NaN
    },
    "newton_converged_ratio": {
      "mean": NaN,
      "std": NaN,
      "min": NaN,
      "max": NaN
    }
  },
  "neural_plus_newton": {
    "mae": {
      "mean": 2.591935666496652e-10,
      "std": 5.550745244965243e-16,
      "min": 2.591922061624879e-10,
      "max": 2.591960094227247e-10
    },
    "rmse": {
      "mean": 3.4548228815390323e-09,
      "std": 1.0637350664865748e-15,
      "min": 3.454820497483097e-09,
      "max": 3.4548252167686764e-09
    },
    "r2": {
      "mean": 1.0,
      "std": 0.0,
      "min": 1.0,
      "max": 1.0
    },
    "valid_ratio": {
      "mean": 1.0,
      "std": 0.0,
      "min": 1.0,
      "max": 1.0
    },
    "residual_mean": {
      "mean": 7.055350460853696e-14,
      "std": 7.799707759179557e-15,
      "min": 5.686361258722589e-14,
      "max": 8.590525178145056e-14
    },
    "residual_median": {
      "mean": 9.825473767932635e-16,
      "std": 2.3638009899920805e-16,
      "min": 8.881784197001252e-16,
      "max": 1.7763568394002505e-15
    },
    "residual_p90": {
      "mean": 2.4534566045453217e-13,
      "std": 4.014974284294104e-14,
      "min": 1.7053025658242404e-13,
      "max": 3.197442310920451e-13
    },
    "max_abs_error": {
      "mean": 7.416904038715089e-07,
      "std": 4.474203911093822e-13,
      "min": 7.416892955358634e-07,
      "max": 7.416911580460095e-07
    },
    "newton_iter_mean": {
      "mean": 2.6119485,
      "std": 0.0733120186380495,
      "min": 2.46105,
      "max": 2.742675
    },
    "newton_iter_median": {
      "mean": 2.94,
      "std": 0.23989793748209523,
      "min": 2.0,
      "max": 3.0
    },
    "newton_iter_p90": {
      "mean": 3.0,
      "std": 0.0,
      "min": 3.0,
      "max": 3.0
    },
    "newton_converged_ratio": {
      "mean": 1.0,
      "std": 0.0,
      "min": 1.0,
      "max": 1.0
    }
  }
}{
  "heuristic_direct": {
    "mae": {
      "mean": 0.09710039504512848,
      "std": 0.0,
      "min": 0.09710039504512848,
      "max": 0.09710039504512848
    },
    "rmse": {
      "mean": 0.21025729362344586,
      "std": 0.0,
      "min": 0.21025729362344586,
      "max": 0.21025729362344586
    },
    "r2": {
      "mean": 0.8834746074576723,
      "std": 0.0,
      "min": 0.8834746074576723,
      "max": 0.8834746074576723
    },
    "valid_ratio": {
      "mean": 1.0,
      "std": 0.0,
      "min": 1.0,
      "max": 1.0
    },
    "residual_mean": {
      "mean": 103.26627398539918,
      "std": 0.0,
      "min": 103.26627398539918,
      "max": 103.26627398539918
    },
    "residual_median": {
      "mean": 0.9996288204594204,
      "std": 0.0,
      "min": 0.9996288204594204,
      "max": 0.9996288204594204
    },
    "residual_p90": {
      "mean": 126.51098781810394,
      "std": 0.0,
      "min": 126.51098781810394,
      "max": 126.51098781810394
    },
    "max_abs_error": {
      "mean": 3.5184905443307604,
      "std": 0.0,
      "min": 3.5184905443307604,
      "max": 3.5184905443307604
    },
    "newton_iter_mean": {
      "mean": NaN,
      "std": NaN,
      "min": NaN,
      "max": NaN
    },
    "newton_iter_median": {
      "mean": NaN,
      "std": NaN,
      "min": NaN,
      "max": NaN
    },
    "newton_iter_p90": {
      "mean": NaN,
      "std": NaN,
      "min": NaN,
      "max": NaN
    },
    "newton_converged_ratio": {
      "mean": NaN,
      "std": NaN,
      "min": NaN,
      "max": NaN
    }
  },
  "heuristic_plus_newton": {
    "mae": {
      "mean": 2.6035335929106006e-10,
      "std": 0.0,
      "min": 2.6035335929106006e-10,
      "max": 2.6035335929106006e-10
    },
    "rmse": {
      "mean": 3.6813604170292685e-09,
      "std": 0.0,
      "min": 3.6813604170292685e-09,
      "max": 3.6813604170292685e-09
    },
    "r2": {
      "mean": 1.0,
      "std": 0.0,
      "min": 1.0,
      "max": 1.0
    },
    "valid_ratio": {
      "mean": 1.0,
      "std": 0.0,
      "min": 1.0,
      "max": 1.0
    },
    "residual_mean": {
      "mean": 5.513936018776112e-12,
      "std": 0.0,
      "min": 5.513936018776112e-12,
      "max": 5.513936018776112e-12
    },
    "residual_median": {
      "mean": 8.881784197001252e-16,
      "std": 0.0,
      "min": 8.881784197001252e-16,
      "max": 8.881784197001252e-16
    },
    "residual_p90": {
      "mean": 1.7009171848769703e-13,
      "std": 0.0,
      "min": 1.7009171848769703e-13,
      "max": 1.7009171848769703e-13
    },
    "max_abs_error": {
      "mean": 8.615343933815467e-07,
      "std": 0.0,
      "min": 8.615343933815467e-07,
      "max": 8.615343933815467e-07
    },
    "newton_iter_mean": {
      "mean": 5.925075,
      "std": 0.0,
      "min": 5.925075,
      "max": 5.925075
    },
    "newton_iter_median": {
      "mean": 6.0,
      "std": 0.0,
      "min": 6.0,
      "max": 6.0
    },
    "newton_iter_p90": {
      "mean": 9.0,
      "std": 0.0,
      "min": 9.0,
      "max": 9.0
    },
    "newton_converged_ratio": {
      "mean": 0.9999,
      "std": 0.0,
      "min": 0.9999,
      "max": 0.9999
    }
  },
  "neural_direct": {
    "mae": {
      "mean": 0.0008886954874488736,
      "std": 0.00010524549015505508,
      "min": 0.0007389117645286316,
      "max": 0.001141542578706574
    },
    "rmse": {
      "mean": 0.0016686686119134536,
      "std": 0.00017589756085477308,
      "min": 0.0014113975242865883,
      "max": 0.0020153259755145442
    },
    "r2": {
      "mean": 0.9999925807110079,
      "std": 1.5922156199354907e-06,
      "min": 0.9999892944486304,
      "max": 0.9999947493008247
    },
    "valid_ratio": {
      "mean": 1.0,
      "std": 0.0,
      "min": 1.0,
      "max": 1.0
    },
    "residual_mean": {
      "mean": 0.01713997873315217,
      "std": 0.0044160009293140925,
      "min": 0.009505910073653107,
      "max": 0.032272403501545935
    },
    "residual_median": {
      "mean": 0.0026986095139342014,
      "std": 0.0004426578630968367,
      "min": 0.00198797367025888,
      "max": 0.0035955888906646083
    },
    "residual_p90": {
      "mean": 0.01927283926017139,
      "std": 0.005051665142956357,
      "min": 0.012075736043817637,
      "max": 0.03467256395147549
    },
    "max_abs_error": {
      "mean": 0.06283407916209222,
      "std": 0.011749084108027332,
      "min": 0.03796073232925323,
      "max": 0.08839906540592057
    },
    "newton_iter_mean": {
      "mean": NaN,
      "std": NaN,
      "min": NaN,
      "max": NaN
    },
    "newton_iter_median": {
      "mean": NaN,
      "std": NaN,
      "min": NaN,
      "max": NaN
    },
    "newton_iter_p90": {
      "mean": NaN,
      "std": NaN,
      "min": NaN,
      "max": NaN
    },
    "newton_converged_ratio": {
      "mean": NaN,
      "std": NaN,
      "min": NaN,
      "max": NaN
    }
  },
  "neural_plus_newton": {
    "mae": {
      "mean": 2.591935666496652e-10,
      "std": 5.550745244965243e-16,
      "min": 2.591922061624879e-10,
      "max": 2.591960094227247e-10
    },
    "rmse": {
      "mean": 3.4548228815390323e-09,
      "std": 1.0637350664865748e-15,
      "min": 3.454820497483097e-09,
      "max": 3.4548252167686764e-09
    },
    "r2": {
      "mean": 1.0,
      "std": 0.0,
      "min": 1.0,
      "max": 1.0
    },
    "valid_ratio": {
      "mean": 1.0,
      "std": 0.0,
      "min": 1.0,
      "max": 1.0
    },
    "residual_mean": {
      "mean": 7.055350460853696e-14,
      "std": 7.799707759179557e-15,
      "min": 5.686361258722589e-14,
      "max": 8.590525178145056e-14
    },
    "residual_median": {
      "mean": 9.825473767932635e-16,
      "std": 2.3638009899920805e-16,
      "min": 8.881784197001252e-16,
      "max": 1.7763568394002505e-15
    },
    "residual_p90": {
      "mean": 2.4534566045453217e-13,
      "std": 4.014974284294104e-14,
      "min": 1.7053025658242404e-13,
      "max": 3.197442310920451e-13
    },
    "max_abs_error": {
      "mean": 7.416904038715089e-07,
      "std": 4.474203911093822e-13,
      "min": 7.416892955358634e-07,
      "max": 7.416911580460095e-07
    },
    "newton_iter_mean": {
      "mean": 2.6119485,
      "std": 0.0733120186380495,
      "min": 2.46105,
      "max": 2.742675
    },
    "newton_iter_median": {
      "mean": 2.94,
      "std": 0.23989793748209523,
      "min": 2.0,
      "max": 3.0
    },
    "newton_iter_p90": {
      "mean": 3.0,
      "std": 0.0,
      "min": 3.0,
      "max": 3.0
    },
    "newton_converged_ratio": {
      "mean": 1.0,
      "std": 0.0,
      "min": 1.0,
      "max": 1.0
    }
  }
}